RTL verification/main5.v
module RAM_Controller #(
    parameter DATA_WIDTH = 16, // to maintain 
    parameter ADDR_WIDTH = 15, // address width as per no.of blocks
    parameter BANKS      = 16, // max no. of memory location that supported this code is 16  
    parameter X = 8,
    parameter Y = 8
)(
    input  wire clk,
    input  wire [CMD_WR_WIDTH-1:0] cmd_wr,
    input  wire [CMD_RD_WIDTH-1:0] cmd_rd,
    output reg [DATA_WIDTH-1:0] data_out
);

    localparam CMD_WR_WIDTH = 2 + 4 + ADDR_WIDTH + 2 + DATA_WIDTH;
    localparam CMD_RD_WIDTH = 1 + 4 + ADDR_WIDTH + 2;

    integer i, b;

    wire [1:0] op_wr = cmd_wr[CMD_WR_WIDTH-1 : CMD_WR_WIDTH-2];
    wire [3:0] bank_wr = cmd_wr[CMD_WR_WIDTH-3 : CMD_WR_WIDTH-6]; // 4-bits represent the memory number
    wire [ADDR_WIDTH-1:0] addr_wr = cmd_wr[DATA_WIDTH+ADDR_WIDTH+1 : DATA_WIDTH+2]; // address location
    wire [1:0]dtype_wr = cmd_wr[DATA_WIDTH+1:DATA_WIDTH]; // datain 
    wire [DATA_WIDTH-1:0] din = cmd_wr[DATA_WIDTH-1:0]; // data in format

    wire op_rd = cmd_rd[CMD_RD_WIDTH-1];
    wire [3:0] bank_rd = cmd_rd[CMD_RD_WIDTH-2 : CMD_RD_WIDTH-5]; 
    wire [ADDR_WIDTH-1:0] addr_rd = cmd_rd[ADDR_WIDTH +1:2]; // required format
    wire [1:0]format_rd = cmd_rd[1:0];
    (* ram_style="block" *) reg [DATA_WIDTH+Y-1:0] mem [0:BANKS-1][0:(1<<ADDR_WIDTH)-1];
  initial begin
    data_out = {DATA_WIDTH{1'b0}};
end


    function [DATA_WIDTH+Y-1:0] convert_input;
    input [DATA_WIDTH-1:0] value;
    input [1:0] dtype;
    reg sign;
    reg [6:0] exp;
    reg [7:0] mant;
    reg [8:0] mant_full;
    integer unbiased_exp;
    integer shifted_value;
    integer scaled;
    begin
        case (dtype)
            2'b00: begin
                convert_input = {{Y{1'b0}}, value};
            end
            2'b01: begin
                convert_input = {value, {Y{1'b0}}};
            end
            2'b10: begin
                sign       = value[15];
                exp        = value[14:8];
                mant       = value[7:0];
                mant_full  = (exp == 0) ? {1'b0, mant} : {1'b1, mant};
                unbiased_exp = exp - 63;
                shifted_value = mant_full << (Y + unbiased_exp);
                shifted_value = shifted_value >> 8;
                if (sign)
                    scaled = -shifted_value;
                else
                    scaled = shifted_value;
                if (scaled > ((1 << (DATA_WIDTH+Y-1)) - 1))
                    scaled = ((1 << (DATA_WIDTH+Y-1)) - 1);
                else if (scaled < -(1 << (DATA_WIDTH+Y-1)))
                    scaled = -(1 << (DATA_WIDTH+Y-1));
                convert_input = scaled[DATA_WIDTH+Y-1:0];
            end
            default: begin
                convert_input = {{(DATA_WIDTH+Y){1'b0}}};
            end
        endcase
    end
endfunction

    function [DATA_WIDTH-1:0] convert_output;
    input signed [DATA_WIDTH+Y-1:0] value;
    input [1:0] format;
    reg sign;
    reg [DATA_WIDTH+Y-1:0] abs_value;
    integer exp_unbiased;
    integer leading_bit_pos;
    reg [7:0] mantissa;
    reg [6:0] exponent;
    integer i;
    begin
        case (format)
            2'b00: begin
                convert_output = value[DATA_WIDTH-1:0];
            end
            2'b01: begin
                convert_output = value >> Y;
            end
            2'b10: begin
                sign = value[DATA_WIDTH+Y-1];
                abs_value = (sign) ? -value : value;

                leading_bit_pos = -1;
                for (i = DATA_WIDTH+Y-1; i >= 0; i = i - 1)
                    if (abs_value[i] && leading_bit_pos < 0)
                        leading_bit_pos = i;

                if (leading_bit_pos >= 0) begin
                    exp_unbiased = leading_bit_pos - Y;
                    exponent = exp_unbiased + 63;
                    if (leading_bit_pos > 8)
                        mantissa = (abs_value >> (leading_bit_pos - 8)) & 8'hFF;
                    else
                        mantissa = (abs_value << (8 - leading_bit_pos)) & 8'hFF;
                    convert_output = {sign, exponent, mantissa};
                end else begin
                    convert_output = 16'b0;
                end
            end
            default: begin
                convert_output = {DATA_WIDTH{1'b0}};
            end
        endcase
    end
endfunction


    always @(negedge clk) begin
        case(op_wr)
            2'b10: begin
                for (b=0; b<BANKS; b=b+1)
                    for (i=0; i<(1<<ADDR_WIDTH); i=i+1)
                        mem[b][i] <= 16'd0;
            end
            2'b11: begin
                if (bank_wr < BANKS)
                    mem[bank_wr][addr_wr] <= 16'd0;
            end
            2'b01: begin
                if (bank_wr < BANKS)
                    mem[bank_wr][addr_wr] <= convert_input(din, dtype_wr);
            end
        endcase
    end

    always @(negedge clk) begin
        if (op_rd == 1'b1 && bank_rd < BANKS)
            data_out <= convert_output(mem[bank_rd][addr_rd], format_rd);
    end

endmodule

RTL verification/tb8.v
`timescale 1ns / 1ps

module tb_RAM_Controller;

    localparam DATA_WIDTH = 16;
    localparam ADDR_WIDTH = 4;
    localparam BANKS      = 2;

    localparam CMD_WR_WIDTH = 2 + 4 + ADDR_WIDTH + 2 + DATA_WIDTH;
    localparam CMD_RD_WIDTH = 1 + 4 + ADDR_WIDTH + 2;

    reg clk;
    reg [CMD_WR_WIDTH-1:0] cmd_wr;
    reg [CMD_RD_WIDTH-1:0] cmd_rd;
    wire [DATA_WIDTH-1:0] data_out;

    // Instantiate DUT with default X,Y = 8,8
    RAM_Controller #(
        .DATA_WIDTH(DATA_WIDTH),
        .ADDR_WIDTH(ADDR_WIDTH),
        .BANKS(BANKS),
        .X(8),
        .Y(8)
    ) DUT (
        .clk(clk),
        .cmd_wr(cmd_wr),
        .cmd_rd(cmd_rd),
        .data_out(data_out)
    );

    // Clock Generation
    initial clk = 0;
    always #5 clk = ~clk;

    reg [15:0] test_values [0:7];
    reg [15:0] fp4_values [0:3];
    reg [15:0] fp8_values [0:3];
    reg [15:0] fp16_values [0:3];
    integer i;

    initial begin
        $dumpfile("waveform.vcd");
        $dumpvars(0, tb_RAM_Controller);

        cmd_wr = 0;
        cmd_rd = 0;

        // Initialize integer/fixed-point test values
        test_values[0] = 16'h0001;
        test_values[1] = 16'h00F0;
        test_values[2] = 16'h0F00;
        test_values[3] = 16'h7FFF;
        test_values[4] = 16'h8000;
        test_values[5] = 16'hF000;
        test_values[6] = 16'h1234;
        test_values[7] = 16'hABCD;

        // Example FP4 (1 sign, 2 exp, 1 mant) stored in 16 bits (top bits used)
        // Format: [15] sign | [14:13] exp | [12] mant | rest 0
        fp4_values[0] = 16'b0_01_1_000000000000; // small positive number
        fp4_values[1] = 16'b0_10_0_000000000000; // ~2.0
        fp4_values[2] = 16'b1_10_0_000000000000; // -2.0
        fp4_values[3] = 16'b0_11_1_000000000000; // near max FP4 value

        // Example FP8 (1 sign, 4 exp, 3 mant) stored in 16 bits
        // Format: [15] sign | [14:11] exp | [10:8] mant
        fp8_values[0] = 16'b0_0111_000_00000000; // +1.0 approx
        fp8_values[1] = 16'b1_0111_000_00000000; // -1.0 approx
        fp8_values[2] = 16'b0_1000_000_00000000; // +2.0 approx
        fp8_values[3] = 16'b0_1001_000_00000000; // +4.0 approx

        // FP16 examples (IEEE 754 half precision)
        fp16_values[0] = 16'b0_0111110_00000000; // +0.5
        fp16_values[1] = 16'b0_0111111_00000000; // +1.0
        fp16_values[2] = 16'b1_0111111_00000000; // -1.0
        fp16_values[3] = 16'b0_1000000_00000000; // +2.0

        $display("===== Starting RAM_Controller Test (FP4, FP8, FP16) =====");

        // === Integer / Fixed-Point ===
        for (i = 0; i < 8; i = i + 1) begin
            @(posedge clk);
            cmd_wr <= {2'b01, 4'd0, i[ADDR_WIDTH-1:0], 2'b01, test_values[i]};
            @(posedge clk);
            cmd_wr <= 0;
            @(posedge clk);
            cmd_rd <= {1'b1, 4'd0, i[ADDR_WIDTH-1:0], 2'b01};
            @(posedge clk);
            $display("[INT/Q] Addr=%0d Write=%h Read=%h", i, test_values[i], data_out);
            cmd_rd <= 0;
        end

        // === FP4 ===
        $display("===== Testing FP4 Conversion =====");
        for (i = 0; i < 4; i = i + 1) begin
            @(posedge clk);
            cmd_wr <= {2'b01, 4'd0, i[ADDR_WIDTH-1:0], 2'b10, fp4_values[i]};
            @(posedge clk);
            cmd_wr <= 0;
            @(posedge clk);
            cmd_rd <= {1'b1, 4'd0, i[ADDR_WIDTH-1:0], 2'b10};
            @(posedge clk);
            $display("[FP4] Addr=%0d Write=%b ReadBack=%b", i, fp4_values[i], data_out);
            cmd_rd <= 0;
        end

        // === FP8 ===
        $display("===== Testing FP8 Conversion =====");
        for (i = 0; i < 4; i = i + 1) begin
            @(posedge clk);
            cmd_wr <= {2'b01, 4'd0, i[ADDR_WIDTH-1:0], 2'b10, fp8_values[i]};
            @(posedge clk);
            cmd_wr <= 0;
            @(posedge clk);
            cmd_rd <= {1'b1, 4'd0, i[ADDR_WIDTH-1:0], 2'b10};
            @(posedge clk);
            $display("[FP8] Addr=%0d Write=%b ReadBack=%b", i, fp8_values[i], data_out);
            cmd_rd <= 0;
        end

        // === FP16 ===
        $display("===== Testing FP16 Conversion =====");
        for (i = 0; i < 4; i = i + 1) begin
            @(posedge clk);
            cmd_wr <= {2'b01, 4'd0, i[ADDR_WIDTH-1:0], 2'b10, fp16_values[i]};
            @(posedge clk);
            cmd_wr <= 0;
            @(posedge clk);
            cmd_rd <= {1'b1, 4'd0, i[ADDR_WIDTH-1:0], 2'b10};
            @(posedge clk);
            $display("[FP16] Addr=%0d Write=%b ReadBack=%b", i, fp16_values[i], data_out);
            cmd_rd <= 0;
        end

        $display("===== All Tests Completed Successfully =====");
        $finish;
    end

endmodule

RTL verification/waveform.vcd
$date
	Wed Sep 24 20:20:46 2025
$end
$version
	Icarus Verilog
$end
$timescale
	1ps
$end
$scope module tb_RAM_Controller $end
$var wire 16 ! data_out [15:0] $end
$var reg 1 " clk $end
$var reg 11 # cmd_rd [10:0] $end
$var reg 28 $ cmd_wr [27:0] $end
$var integer 32 % i [31:0] $end
$scope module DUT $end
$var wire 1 " clk $end
$var wire 11 & cmd_rd [10:0] $end
$var wire 28 ' cmd_wr [27:0] $end
$var wire 2 ( op_wr [1:0] $end
$var wire 1 ) op_rd $end
$var wire 2 * format_rd [1:0] $end
$var wire 2 + dtype_wr [1:0] $end
$var wire 16 , din [15:0] $end
$var wire 4 - bank_wr [3:0] $end
$var wire 4 . bank_rd [3:0] $end
$var wire 4 / addr_wr [3:0] $end
$var wire 4 0 addr_rd [3:0] $end
$var reg 16 1 data_out [15:0] $end
$var integer 32 2 b [31:0] $end
$var integer 32 3 i [31:0] $end
$scope function convert_input $end
$var reg 2 4 dtype [1:0] $end
$var reg 7 5 exp [6:0] $end
$var reg 8 6 mant [7:0] $end
$var reg 9 7 mant_full [8:0] $end
$var reg 1 8 sign $end
$var reg 16 9 value [15:0] $end
$var integer 32 : scaled [31:0] $end
$var integer 32 ; shifted_value [31:0] $end
$var integer 32 < unbiased_exp [31:0] $end
$upscope $end
$scope function convert_output $end
$var reg 24 = abs_value [23:0] $end
$var reg 7 > exponent [6:0] $end
$var reg 2 ? format [1:0] $end
$var reg 8 @ mantissa [7:0] $end
$var reg 1 A sign $end
$var reg 24 B value [23:0] $end
$var integer 32 C exp_unbiased [31:0] $end
$var integer 32 D i [31:0] $end
$var integer 32 E leading_bit_pos [31:0] $end
$upscope $end
$upscope $end
$upscope $end
$enddefinitions $end
#0
$dumpvars
bx E
bx D
bx C
bx B
xA
bx @
bx ?
bx >
bx =
bx <
bx ;
bx :
bx 9
x8
bx 7
bx 6
bx 5
bx 4
bx 3
bx 2
b0 1
b0 0
b0 /
b0 .
b0 -
b0 ,
b0 +
b0 *
0)
b0 (
b0 '
b0 &
b0 %
b0 $
b0 #
0"
b0 !
$end
#5000
b1 (
b1 +
b1 ,
b100000000010000000000000001 $
b100000000010000000000000001 '
1"
#10000
b1 9
b1 4
0"
#15000
b0 (
b0 +
b0 ,
b0 $
b0 '
1"
#20000
0"
#25000
1)
b1 *
b10000000001 #
b10000000001 &
1"
#30000
b1 !
b1 1
b100000000 B
b1 ?
0"
#35000
0)
b0 *
b0 #
b0 &
b1 %
1"
#40000
0"
#45000
b1 (
b1 /
b1 +
b11110000 ,
b100000001010000000011110000 $
b100000001010000000011110000 '
1"
#50000
b11110000 9
0"
#55000
b0 (
b0 /
b0 +
b0 ,
b0 $
b0 '
1"
#60000
0"
#65000
1)
b1 0
b1 *
b10000000101 #
b10000000101 &
1"
#70000
b11110000 !
b11110000 1
b1111000000000000 B
0"
#75000
0)
b0 0
b0 *
b0 #
b0 &
b10 %
1"
#80000
0"
#85000
b1 (
b10 /
b1 +
b111100000000 ,
b100000010010000111100000000 $
b100000010010000111100000000 '
1"
#90000
b111100000000 9
0"
#95000
b0 (
b0 /
b0 +
b0 ,
b0 $
b0 '
1"
#100000
0"
#105000
1)
b10 0
b1 *
b10000001001 #
b10000001001 &
1"
#110000
b111100000000 !
b111100000000 1
b11110000000000000000 B
0"
#115000
0)
b0 0
b0 *
b0 #
b0 &
b11 %
1"
#120000
0"
#125000
b1 (
b11 /
b1 +
b111111111111111 ,
b100000011010111111111111111 $
b100000011010111111111111111 '
1"
#130000
b111111111111111 9
0"
#135000
b0 (
b0 /
b0 +
b0 ,
b0 $
b0 '
1"
#140000
0"
#145000
1)
b11 0
b1 *
b10000001101 #
b10000001101 &
1"
#150000
b111111111111111 !
b111111111111111 1
b11111111111111100000000 B
0"
#155000
0)
b0 0
b0 *
b0 #
b0 &
b100 %
1"
#160000
0"
#165000
b1 (
b100 /
b1 +
b1000000000000000 ,
b100000100011000000000000000 $
b100000100011000000000000000 '
1"
#170000
b1000000000000000 9
0"
#175000
b0 (
b0 /
b0 +
b0 ,
b0 $
b0 '
1"
#180000
0"
#185000
1)
b100 0
b1 *
b10000010001 #
b10000010001 &
1"
#190000
b1000000000000000 !
b1000000000000000 1
b100000000000000000000000 B
0"
#195000
0)
b0 0
b0 *
b0 #
b0 &
b101 %
1"
#200000
0"
#205000
b1 (
b101 /
b1 +
b1111000000000000 ,
b100000101011111000000000000 $
b100000101011111000000000000 '
1"
#210000
b1111000000000000 9
0"
#215000
b0 (
b0 /
b0 +
b0 ,
b0 $
b0 '
1"
#220000
0"
#225000
1)
b101 0
b1 *
b10000010101 #
b10000010101 &
1"
#230000
b1111000000000000 !
b1111000000000000 1
b111100000000000000000000 B
0"
#235000
0)
b0 0
b0 *
b0 #
b0 &
b110 %
1"
#240000
0"
#245000
b1 (
b110 /
b1 +
b1001000110100 ,
b100000110010001001000110100 $
b100000110010001001000110100 '
1"
#250000
b1001000110100 9
0"
#255000
b0 (
b0 /
b0 +
b0 ,
b0 $
b0 '
1"
#260000
0"
#265000
1)
b110 0
b1 *
b10000011001 #
b10000011001 &
1"
#270000
b1001000110100 !
b1001000110100 1
b100100011010000000000 B
0"
#275000
0)
b0 0
b0 *
b0 #
b0 &
b111 %
1"
#280000
0"
#285000
b1 (
b111 /
b1 +
b1010101111001101 ,
b100000111011010101111001101 $
b100000111011010101111001101 '
1"
#290000
b1010101111001101 9
0"
#295000
b0 (
b0 /
b0 +
b0 ,
b0 $
b0 '
1"
#300000
0"
#305000
1)
b111 0
b1 *
b10000011101 #
b10000011101 &
1"
#310000
b1010101111001101 !
b1010101111001101 1
b101010111100110100000000 B
0"
#315000
0)
b0 0
b0 *
b0 #
b0 &
b0 %
1"
#320000
0"
#325000
b1 (
b10 +
b11000000000000 ,
b100000000100011000000000000 $
b100000000100011000000000000 '
1"
#330000
b0 :
b0 ;
b11111111111111111111111111110001 <
b100000000 7
b0 6
b110000 5
08
b11000000000000 9
b10 4
0"
#335000
b0 (
b0 +
b0 ,
b0 $
b0 '
1"
#340000
0"
#345000
1)
b10 *
b10000000010 #
b10000000010 &
1"
#350000
b0 !
b0 1
b11111111111111111111111111111111 D
b11111111111111111111111111111111 E
b0 =
0A
b0 B
b10 ?
0"
#355000
0)
b0 *
b0 #
b0 &
b1 %
1"
#360000
0"
#365000
b1 (
b1 /
b10 +
b100000000000000 ,
b100000001100100000000000000 $
b100000001100100000000000000 '
1"
#370000
b1000000000 :
b1000000000 ;
b1 <
b1000000 5
b100000000000000 9
0"
#375000
b0 (
b0 /
b0 +
b0 ,
b0 $
b0 '
1"
#380000
0"
#385000
1)
b1 0
b10 *
b10000000110 #
b10000000110 &
1"
#390000
b100000000000000 !
b100000000000000 1
b0 @
b1000000 >
b1 C
b1001 E
b11111111111111111111111111111111 D
b1000000000 =
b1000000000 B
0"
#395000
0)
b0 0
b0 *
b0 #
b0 &
b10 %
1"
#400000
0"
#405000
b1 (
b10 /
b10 +
b1100000000000000 ,
b100000010101100000000000000 $
b100000010101100000000000000 '
1"
#410000
b11111111111111111111111000000000 :
b1000000000 ;
18
b1100000000000000 9
0"
#415000
b0 (
b0 /
b0 +
b0 ,
b0 $
b0 '
1"
#420000
0"
#425000
1)
b10 0
b10 *
b10000001010 #
b10000001010 &
1"
#430000
b1100000000000000 !
b1100000000000000 1
b11111111111111111111111111111111 D
b1001 E
1A
b111111111111111000000000 B
0"
#435000
0)
b0 0
b0 *
b0 #
b0 &
b11 %
1"
#440000
0"
#445000
b1 (
b11 /
b10 +
b111000000000000 ,
b100000011100111000000000000 $
b100000011100111000000000000 '
1"
#450000
b0 :
b0 ;
b110001 <
b1110000 5
08
b111000000000000 9
0"
#455000
b0 (
b0 /
b0 +
b0 ,
b0 $
b0 '
1"
#460000
0"
#465000
1)
b11 0
b10 *
b10000001110 #
b10000001110 &
1"
#470000
b0 !
b0 1
b11111111111111111111111111111111 D
b11111111111111111111111111111111 E
b0 =
0A
b0 B
0"
#475000
0)
b0 0
b0 *
b0 #
b0 &
b0 %
1"
#480000
0"
#485000
b1 (
b10 +
b11100000000000 ,
b100000000100011100000000000 $
b100000000100011100000000000 '
1"
#490000
b10 :
b10 ;
b11111111111111111111111111111001 <
b111000 5
b11100000000000 9
0"
#495000
b0 (
b0 +
b0 ,
b0 $
b0 '
1"
#500000
0"
#505000
1)
b10 *
b10000000010 #
b10000000010 &
1"
#510000
b11100000000000 !
b11100000000000 1
b111000 >
b11111111111111111111111111111001 C
b1 E
b11111111111111111111111111111111 D
b10 =
b10 B
0"
#515000
0)
b0 *
b0 #
b0 &
b1 %
1"
#520000
0"
#525000
b1 (
b1 /
b10 +
b1011100000000000 ,
b100000001101011100000000000 $
b100000001101011100000000000 '
1"
#530000
b11111111111111111111111111111110 :
b10 ;
18
b1011100000000000 9
0"
#535000
b0 (
b0 /
b0 +
b0 ,
b0 $
b0 '
1"
#540000
0"
#545000
1)
b1 0
b10 *
b10000000110 #
b10000000110 &
1"
#550000
b1011100000000000 !
b1011100000000000 1
b11111111111111111111111111111111 D
b1 E
1A
b111111111111111111111110 B
0"
#555000
0)
b0 0
b0 *
b0 #
b0 &
b10 %
1"
#560000
0"
#565000
b1 (
b10 /
b10 +
b100000000000000 ,
b100000010100100000000000000 $
b100000010100100000000000000 '
1"
#570000
b1000000000 :
b1000000000 ;
b1 <
b1000000 5
08
b100000000000000 9
0"
#575000
b0 (
b0 /
b0 +
b0 ,
b0 $
b0 '
1"
#580000
0"
#585000
1)
b10 0
b10 *
b10000001010 #
b10000001010 &
1"
#590000
b100000000000000 !
b100000000000000 1
b1000000 >
b1 C
b11111111111111111111111111111111 D
b1001 E
b1000000000 =
0A
b1000000000 B
0"
#595000
0)
b0 0
b0 *
b0 #
b0 &
b11 %
1"
#600000
0"
#605000
b1 (
b11 /
b10 +
b100100000000000 ,
b100000011100100100000000000 $
b100000011100100100000000000 '
1"
#610000
b100000000000000000 :
b100000000000000000 ;
b1001 <
b1001000 5
b100100000000000 9
0"
#615000
b0 (
b0 /
b0 +
b0 ,
b0 $
b0 '
1"
#620000
0"
#625000
1)
b11 0
b10 *
b10000001110 #
b10000001110 &
1"
#630000
b100100000000000 !
b100100000000000 1
b1001000 >
b1001 C
b11111111111111111111111111111111 D
b10001 E
b100000000000000000 =
b100000000000000000 B
0"
#635000
0)
b0 0
b0 *
b0 #
b0 &
b0 %
1"
#640000
0"
#645000
b1 (
b10 +
b11111000000000 ,
b100000000100011111000000000 $
b100000000100011111000000000 '
1"
#650000
b10000000 :
b10000000 ;
b11111111111111111111111111111111 <
b111110 5
b11111000000000 9
0"
#655000
b0 (
b0 +
b0 ,
b0 $
b0 '
1"
#660000
0"
#665000
1)
b10 *
b10000000010 #
b10000000010 &
1"
#670000
b11111000000000 !
b11111000000000 1
b111110 >
b11111111111111111111111111111111 C
b11111111111111111111111111111111 D
b111 E
b10000000 =
b10000000 B
0"
#675000
0)
b0 *
b0 #
b0 &
b1 %
1"
#680000
0"
#685000
b1 (
b1 /
b10 +
b11111100000000 ,
b100000001100011111100000000 $
b100000001100011111100000000 '
1"
#690000
b100000000 :
b100000000 ;
b0 <
b111111 5
b11111100000000 9
0"
#695000
b0 (
b0 /
b0 +
b0 ,
b0 $
b0 '
1"
#700000
0"
#705000
1)
b1 0
b10 *
b10000000110 #
b10000000110 &
1"
#710000
b11111100000000 !
b11111100000000 1
b111111 >
b0 C
b11111111111111111111111111111111 D
b1000 E
b100000000 =
b100000000 B
0"
#715000
0)
b0 0
b0 *
b0 #
b0 &
b10 %
1"
#720000
0"
#725000
b1 (
b10 /
b10 +
b1011111100000000 ,
b100000010101011111100000000 $
b100000010101011111100000000 '
1"
#730000
b11111111111111111111111100000000 :
b100000000 ;
18
b1011111100000000 9
0"
#735000
b0 (
b0 /
b0 +
b0 ,
b0 $
b0 '
1"
#740000
0"
#745000
1)
b10 0
b10 *
b10000001010 #
b10000001010 &
1"
#750000
b1011111100000000 !
b1011111100000000 1
b11111111111111111111111111111111 D
b1000 E
1A
b111111111111111100000000 B
0"
#755000
0)
b0 0
b0 *
b0 #
b0 &
b11 %
1"
#760000
0"
#765000
b1 (
b11 /
b10 +
b100000000000000 ,
b100000011100100000000000000 $
b100000011100100000000000000 '
1"
#770000
b1000000000 :
b1000000000 ;
b1 <
b1000000 5
08
b100000000000000 9
0"
#775000
b0 (
b0 /
b0 +
b0 ,
b0 $
b0 '
1"
#780000
0"
#785000
1)
b11 0
b10 *
b10000001110 #
b10000001110 &
1"
#790000
b100000000000000 !
b100000000000000 1
b1000000 >
b1 C
b11111111111111111111111111111111 D
b1001 E
b1000000000 =
0A
b1000000000 B
0"
#795000
0)
b0 0
b0 *
b0 #
b0 &
b100 %
1"
